[{"line":1,"elements":[{"start_timestamp":"2022-06-01T05:08:46.245Z","line":4,"name":"Validate google search is working","description":"","id":"feature-to-test-google-search-functionality;validate-google-search-is-working","type":"scenario","keyword":"Scenario","steps":[{"result":{"duration":9141335100,"status":"passed"},"line":5,"name":"browser is open","match":{"location":"GoogleImageLink.GoogleSearchSteps.browser_is_open()"},"keyword":"Given "},{"result":{"duration":2700425100,"status":"passed"},"line":6,"name":"user is on google search page","match":{"location":"GoogleImageLink.GoogleSearchSteps.user_is_on_google_search_page()"},"keyword":"And "},{"result":{"duration":390089500,"status":"passed"},"line":7,"name":"user enters a text in search box","match":{"location":"GoogleImageLink.GoogleSearchSteps.user_enters_a_text_in_search_box()"},"keyword":"When "},{"result":{"duration":2849936400,"status":"passed"},"line":8,"name":"hits enter","match":{"location":"GoogleImageLink.GoogleSearchSteps.hits_enter()"},"keyword":"And "},{"result":{"duration":608016100,"status":"passed"},"line":9,"name":"user is navigated to search results","match":{"location":"GoogleImageLink.GoogleSearchSteps.user_is_navigated_to_the_home_page()"},"keyword":"Then "}],"tags":[{"name":"@smoketest"}]}],"name":"feature to test google search functionality","description":"","id":"feature-to-test-google-search-functionality","keyword":"Feature","uri":"file:src/test/resources/Features/GoogleSearch.feature","tags":[]}]